rosrx/__init__.py
rosrx/observabletopic.py
rosrx/observabletopic_1x.py
rosrx/topicobserver.py
rosrx/topicobserver_1x.py
rosrx-0.2.0.dist-info/METADATA
rosrx-0.2.0.dist-info/WHEEL
rosrx-0.2.0.dist-info/top_level.txt
rosrx-0.2.0.dist-info/zip-safe
rosrx-0.2.0.dist-info/RECORD
