Metadata-Version: 2.1
Name: rosrx
Version: 0.2.0
Summary: Reactive extensions for rospy
Home-page: http://github.com/nlinkas/rosrx
Author: Joergen Borgesen
Author-email: jorgen@nlink.no
License: MIT
Keywords: rx rxpy reactive ROS rospy
Platform: UNKNOWN
Requires-Dist: rx (<=3.2,>=1.6)
